{
  "total": 45,
  "fully_active": 5,
  "reviewing_no_config": 23,
  "config_no_reviews": 0,
  "not_configured": 17,
  "has_config_total": 5,
  "has_reviews_total": 28,
  "total_prs_reviewed": 711,
  "total_coderabbit_first_reviews": 297,
  "coderabbit_first_review_pct": 41.8,
  "last_updated": "2026-05-13T02:00:00.120988Z",
  "repos": [
    {
      "name": "okd",
      "url": "https://github.com/okd-project/okd",
      "owner": "okd-project",
      "repo": "okd",
      "team": "OKD",
      "status": "Active",
      "domain": "None",
      "product": "None",
      "has_config": false,
      "config_file": null,
      "has_coderabbit_reviews": false,
      "coderabbit_pr_count": 0,
      "coderabbit_first_review_count": 0,
      "coderabbit_first_review_pct": 0,
      "category": "not_configured",
      "last_updated": "2026-05-13T00:49:55.458777Z"
    },
    {
      "name": "okd-web",
      "url": "https://github.com/okd-project/okd-web",
      "owner": "okd-project",
      "repo": "okd-web",
      "team": "OKD",
      "status": "Active",
      "domain": "None",
      "product": "None",
      "has_config": false,
      "config_file": null,
      "has_coderabbit_reviews": false,
      "coderabbit_pr_count": 0,
      "coderabbit_first_review_count": 0,
      "coderabbit_first_review_pct": 0,
      "category": "not_configured",
      "last_updated": "2026-05-13T00:51:26.404707Z"
    },
    {
      "name": "okderators-catalog-index",
      "url": "https://github.com/okd-project/okderators-catalog-index",
      "owner": "okd-project",
      "repo": "okderators-catalog-index",
      "team": "OKD",
      "status": "Active",
      "domain": "None",
      "product": "None",
      "has_config": false,
      "config_file": null,
      "has_coderabbit_reviews": false,
      "coderabbit_pr_count": 0,
      "coderabbit_first_review_count": 0,
      "coderabbit_first_review_pct": 0,
      "category": "not_configured",
      "last_updated": "2026-05-13T00:52:16.865689Z"
    },
    {
      "name": "dev-scripts",
      "url": "https://github.com/openshift-metal3/dev-scripts",
      "owner": "openshift-metal3",
      "repo": "dev-scripts",
      "team": "Metal Platform",
      "status": "Active",
      "domain": "None",
      "product": "None",
      "has_config": false,
      "config_file": null,
      "has_coderabbit_reviews": false,
      "coderabbit_pr_count": 0,
      "coderabbit_first_review_count": 0,
      "coderabbit_first_review_pct": 0,
      "category": "not_configured",
      "last_updated": "2026-05-13T00:54:29.116036Z"
    },
    {
      "name": "terraform-provider-ironic",
      "url": "https://github.com/openshift-metal3/terraform-provider-ironic",
      "owner": "openshift-metal3",
      "repo": "terraform-provider-ironic",
      "team": "Metal Platform",
      "status": "Active",
      "domain": "None",
      "product": "None",
      "has_config": false,
      "config_file": null,
      "has_coderabbit_reviews": false,
      "coderabbit_pr_count": 0,
      "coderabbit_first_review_count": 0,
      "coderabbit_first_review_pct": 0,
      "category": "not_configured",
      "last_updated": "2026-05-13T00:55:55.700595Z"
    },
    {
      "name": "baremetal-operator",
      "url": "https://github.com/openshift/baremetal-operator",
      "owner": "openshift",
      "repo": "baremetal-operator",
      "team": "Metal Platform",
      "status": "Active",
      "domain": "None",
      "product": "None",
      "has_config": false,
      "config_file": null,
      "has_coderabbit_reviews": true,
      "coderabbit_pr_count": 18,
      "coderabbit_first_review_count": 11,
      "coderabbit_first_review_pct": 61.1,
      "category": "reviewing_no_config",
      "last_updated": "2026-05-13T00:57:36.972379Z"
    },
    {
      "name": "cloud-provider-powervs",
      "url": "https://github.com/openshift/cloud-provider-powervs",
      "owner": "openshift",
      "repo": "cloud-provider-powervs",
      "team": "Multi Architecture",
      "status": "Active",
      "domain": "None",
      "product": "None",
      "has_config": false,
      "config_file": null,
      "has_coderabbit_reviews": true,
      "coderabbit_pr_count": 9,
      "coderabbit_first_review_count": 2,
      "coderabbit_first_review_pct": 22.2,
      "category": "reviewing_no_config",
      "last_updated": "2026-05-13T00:59:12.330252Z"
    },
    {
      "name": "cluster-api-provider-baremetal",
      "url": "https://github.com/openshift/cluster-api-provider-baremetal",
      "owner": "openshift",
      "repo": "cluster-api-provider-baremetal",
      "team": "Metal Platform",
      "status": "Active",
      "domain": "None",
      "product": "None",
      "has_config": false,
      "config_file": null,
      "has_coderabbit_reviews": true,
      "coderabbit_pr_count": 6,
      "coderabbit_first_review_count": 1,
      "coderabbit_first_review_pct": 16.7,
      "category": "reviewing_no_config",
      "last_updated": "2026-05-13T01:00:30.779597Z"
    },
    {
      "name": "cluster-api-provider-metal3",
      "url": "https://github.com/openshift/cluster-api-provider-metal3",
      "owner": "openshift",
      "repo": "cluster-api-provider-metal3",
      "team": "Metal Platform",
      "status": "Active",
      "domain": "None",
      "product": "None",
      "has_config": false,
      "config_file": null,
      "has_coderabbit_reviews": false,
      "coderabbit_pr_count": 0,
      "coderabbit_first_review_count": 0,
      "coderabbit_first_review_pct": 0,
      "category": "not_configured",
      "last_updated": "2026-05-13T01:02:00.894186Z"
    },
    {
      "name": "cluster-baremetal-operator",
      "url": "https://github.com/openshift/cluster-baremetal-operator",
      "owner": "openshift",
      "repo": "cluster-baremetal-operator",
      "team": "Metal Platform",
      "status": "Active",
      "domain": "None",
      "product": "None",
      "has_config": false,
      "config_file": null,
      "has_coderabbit_reviews": true,
      "coderabbit_pr_count": 34,
      "coderabbit_first_review_count": 14,
      "coderabbit_first_review_pct": 41.2,
      "category": "reviewing_no_config",
      "last_updated": "2026-05-13T01:03:40.283057Z"
    },
    {
      "name": "image-customization-controller",
      "url": "https://github.com/openshift/image-customization-controller",
      "owner": "openshift",
      "repo": "image-customization-controller",
      "team": "Metal Platform",
      "status": "Active",
      "domain": "None",
      "product": "None",
      "has_config": false,
      "config_file": null,
      "has_coderabbit_reviews": true,
      "coderabbit_pr_count": 8,
      "coderabbit_first_review_count": 4,
      "coderabbit_first_review_pct": 50.0,
      "category": "reviewing_no_config",
      "last_updated": "2026-05-13T01:05:06.442786Z"
    },
    {
      "name": "installer",
      "url": "https://github.com/openshift/installer",
      "owner": "openshift",
      "repo": "installer",
      "team": "Metal Platform",
      "status": "Active",
      "domain": "None",
      "product": "None",
      "has_config": false,
      "config_file": null,
      "has_coderabbit_reviews": true,
      "coderabbit_pr_count": 49,
      "coderabbit_first_review_count": 24,
      "coderabbit_first_review_pct": 49.0,
      "category": "reviewing_no_config",
      "last_updated": "2026-05-13T01:07:29.066119Z"
    },
    {
      "name": "ironic-agent-image",
      "url": "https://github.com/openshift/ironic-agent-image",
      "owner": "openshift",
      "repo": "ironic-agent-image",
      "team": "Metal Platform",
      "status": "Active",
      "domain": "None",
      "product": "None",
      "has_config": false,
      "config_file": null,
      "has_coderabbit_reviews": true,
      "coderabbit_pr_count": 4,
      "coderabbit_first_review_count": 2,
      "coderabbit_first_review_pct": 50.0,
      "category": "reviewing_no_config",
      "last_updated": "2026-05-13T01:08:51.414763Z"
    },
    {
      "name": "ironic-image",
      "url": "https://github.com/openshift/ironic-image",
      "owner": "openshift",
      "repo": "ironic-image",
      "team": "Metal Platform",
      "status": "Active",
      "domain": "None",
      "product": "None",
      "has_config": false,
      "config_file": null,
      "has_coderabbit_reviews": true,
      "coderabbit_pr_count": 32,
      "coderabbit_first_review_count": 19,
      "coderabbit_first_review_pct": 59.4,
      "category": "reviewing_no_config",
      "last_updated": "2026-05-13T01:10:39.675837Z"
    },
    {
      "name": "ironic-rhcos-downloader",
      "url": "https://github.com/openshift/ironic-rhcos-downloader",
      "owner": "openshift",
      "repo": "ironic-rhcos-downloader",
      "team": "Metal Platform",
      "status": "Active",
      "domain": "None",
      "product": "None",
      "has_config": false,
      "config_file": null,
      "has_coderabbit_reviews": false,
      "coderabbit_pr_count": 0,
      "coderabbit_first_review_count": 0,
      "coderabbit_first_review_pct": 0,
      "category": "not_configured",
      "last_updated": "2026-05-13T01:11:59.989955Z"
    },
    {
      "name": "ironic-standalone-operator",
      "url": "https://github.com/openshift/ironic-standalone-operator",
      "owner": "openshift",
      "repo": "ironic-standalone-operator",
      "team": "Metal Platform",
      "status": "Active",
      "domain": "None",
      "product": "None",
      "has_config": false,
      "config_file": null,
      "has_coderabbit_reviews": false,
      "coderabbit_pr_count": 0,
      "coderabbit_first_review_count": 0,
      "coderabbit_first_review_pct": 0,
      "category": "not_configured",
      "last_updated": "2026-05-13T01:12:44.941654Z"
    },
    {
      "name": "ironic-static-ip-manager",
      "url": "https://github.com/openshift/ironic-static-ip-manager",
      "owner": "openshift",
      "repo": "ironic-static-ip-manager",
      "team": "Metal Platform",
      "status": "Active",
      "domain": "None",
      "product": "None",
      "has_config": false,
      "config_file": null,
      "has_coderabbit_reviews": false,
      "coderabbit_pr_count": 0,
      "coderabbit_first_review_count": 0,
      "coderabbit_first_review_pct": 0,
      "category": "not_configured",
      "last_updated": "2026-05-13T01:14:04.689008Z"
    },
    {
      "name": "machine-os-images",
      "url": "https://github.com/openshift/machine-os-images",
      "owner": "openshift",
      "repo": "machine-os-images",
      "team": "Metal Platform",
      "status": "Active",
      "domain": "None",
      "product": "None",
      "has_config": false,
      "config_file": null,
      "has_coderabbit_reviews": true,
      "coderabbit_pr_count": 9,
      "coderabbit_first_review_count": 1,
      "coderabbit_first_review_pct": 11.1,
      "category": "reviewing_no_config",
      "last_updated": "2026-05-13T01:15:44.421269Z"
    },
    {
      "name": "multiarch-tuning-operator",
      "url": "https://github.com/openshift/multiarch-tuning-operator",
      "owner": "openshift",
      "repo": "multiarch-tuning-operator",
      "team": "Multi Architecture",
      "status": "Active",
      "domain": "None",
      "product": "None",
      "has_config": false,
      "config_file": null,
      "has_coderabbit_reviews": true,
      "coderabbit_pr_count": 36,
      "coderabbit_first_review_count": 33,
      "coderabbit_first_review_pct": 91.7,
      "category": "reviewing_no_config",
      "last_updated": "2026-05-13T01:17:23.549812Z"
    },
    {
      "name": "oc-mirror",
      "url": "https://github.com/openshift/oc-mirror",
      "owner": "openshift",
      "repo": "oc-mirror",
      "team": "CID",
      "status": "Active",
      "domain": "None",
      "product": "None",
      "has_config": false,
      "config_file": null,
      "has_coderabbit_reviews": true,
      "coderabbit_pr_count": 41,
      "coderabbit_first_review_count": 15,
      "coderabbit_first_review_pct": 36.6,
      "category": "reviewing_no_config",
      "last_updated": "2026-05-13T01:19:29.747487Z"
    },
    {
      "name": "openstack-ironic",
      "url": "https://github.com/openshift/openstack-ironic",
      "owner": "openshift",
      "repo": "openstack-ironic",
      "team": "Metal Platform",
      "status": "Active",
      "domain": "None",
      "product": "None",
      "has_config": false,
      "config_file": null,
      "has_coderabbit_reviews": false,
      "coderabbit_pr_count": 0,
      "coderabbit_first_review_count": 0,
      "coderabbit_first_review_pct": 0,
      "category": "not_configured",
      "last_updated": "2026-05-13T01:20:52.322200Z"
    },
    {
      "name": "openstack-ironic-inspector",
      "url": "https://github.com/openshift/openstack-ironic-inspector",
      "owner": "openshift",
      "repo": "openstack-ironic-inspector",
      "team": "Metal Platform",
      "status": "Active",
      "domain": "None",
      "product": "None",
      "has_config": false,
      "config_file": null,
      "has_coderabbit_reviews": false,
      "coderabbit_pr_count": 0,
      "coderabbit_first_review_count": 0,
      "coderabbit_first_review_pct": 0,
      "category": "not_configured",
      "last_updated": "2026-05-13T01:22:09.592053Z"
    },
    {
      "name": "openstack-ironic-lib",
      "url": "https://github.com/openshift/openstack-ironic-lib",
      "owner": "openshift",
      "repo": "openstack-ironic-lib",
      "team": "Metal Platform",
      "status": "Active",
      "domain": "None",
      "product": "None",
      "has_config": false,
      "config_file": null,
      "has_coderabbit_reviews": false,
      "coderabbit_pr_count": 0,
      "coderabbit_first_review_count": 0,
      "coderabbit_first_review_pct": 0,
      "category": "not_configured",
      "last_updated": "2026-05-13T01:23:26.104737Z"
    },
    {
      "name": "openstack-ironic-python-agent",
      "url": "https://github.com/openshift/openstack-ironic-python-agent",
      "owner": "openshift",
      "repo": "openstack-ironic-python-agent",
      "team": "Metal Platform",
      "status": "Active",
      "domain": "None",
      "product": "None",
      "has_config": false,
      "config_file": null,
      "has_coderabbit_reviews": false,
      "coderabbit_pr_count": 0,
      "coderabbit_first_review_count": 0,
      "coderabbit_first_review_pct": 0,
      "category": "not_configured",
      "last_updated": "2026-05-13T01:24:42.716142Z"
    },
    {
      "name": "openstack-sushy",
      "url": "https://github.com/openshift/openstack-sushy",
      "owner": "openshift",
      "repo": "openstack-sushy",
      "team": "Metal Platform",
      "status": "Active",
      "domain": "None",
      "product": "None",
      "has_config": false,
      "config_file": null,
      "has_coderabbit_reviews": false,
      "coderabbit_pr_count": 0,
      "coderabbit_first_review_count": 0,
      "coderabbit_first_review_pct": 0,
      "category": "not_configured",
      "last_updated": "2026-05-13T01:26:02.540368Z"
    },
    {
      "name": "provider-certification-plugins",
      "url": "https://github.com/redhat-openshift-ecosystem/provider-certification-plugins",
      "owner": "redhat-openshift-ecosystem",
      "repo": "provider-certification-plugins",
      "team": "Specialist Platform Team (SPLAT",
      "status": "Active",
      "domain": "None",
      "product": "None",
      "has_config": false,
      "config_file": null,
      "has_coderabbit_reviews": true,
      "coderabbit_pr_count": 5,
      "coderabbit_first_review_count": 4,
      "coderabbit_first_review_pct": 80.0,
      "category": "reviewing_no_config",
      "last_updated": "2026-05-13T01:27:20.994808Z"
    },
    {
      "name": "provider-certification-tool",
      "url": "https://github.com/redhat-openshift-ecosystem/provider-certification-tool",
      "owner": "redhat-openshift-ecosystem",
      "repo": "provider-certification-tool",
      "team": "Specialist Platform Team (SPLAT",
      "status": "Active",
      "domain": "None",
      "product": "None",
      "has_config": false,
      "config_file": null,
      "has_coderabbit_reviews": true,
      "coderabbit_pr_count": 8,
      "coderabbit_first_review_count": 7,
      "coderabbit_first_review_pct": 87.5,
      "category": "reviewing_no_config",
      "last_updated": "2026-05-13T01:29:01.669973Z"
    },
    {
      "name": "edge-hiring",
      "url": "https://github.com/openshift-eng/edge-hiring",
      "owner": "openshift-eng",
      "repo": "edge-hiring",
      "team": "Edge",
      "status": "Active",
      "domain": "None",
      "product": "None",
      "has_config": false,
      "config_file": null,
      "has_coderabbit_reviews": false,
      "coderabbit_pr_count": 0,
      "coderabbit_first_review_count": 0,
      "coderabbit_first_review_pct": 0,
      "category": "not_configured",
      "last_updated": "2026-05-13T01:29:04.186922Z"
    },
    {
      "name": "edge-tooling",
      "url": "https://github.com/openshift-eng/edge-tooling",
      "owner": "openshift-eng",
      "repo": "edge-tooling",
      "team": "Edge",
      "status": "Active",
      "domain": "None",
      "product": "None",
      "has_config": true,
      "config_file": ".coderabbit.yaml",
      "has_coderabbit_reviews": true,
      "coderabbit_pr_count": 37,
      "coderabbit_first_review_count": 37,
      "coderabbit_first_review_pct": 100.0,
      "category": "fully_active",
      "last_updated": "2026-05-13T01:30:53.183660Z"
    },
    {
      "name": "ocpve-toolbox",
      "url": "https://github.com/openshift-eng/ocpve-toolbox",
      "owner": "openshift-eng",
      "repo": "ocpve-toolbox",
      "team": "Edge",
      "status": "Active",
      "domain": "None",
      "product": "None",
      "has_config": false,
      "config_file": null,
      "has_coderabbit_reviews": false,
      "coderabbit_pr_count": 0,
      "coderabbit_first_review_count": 0,
      "coderabbit_first_review_pct": 0,
      "category": "not_configured",
      "last_updated": "2026-05-13T01:30:55.658539Z"
    },
    {
      "name": "two-node-toolbox",
      "url": "https://github.com/openshift-eng/two-node-toolbox",
      "owner": "openshift-eng",
      "repo": "two-node-toolbox",
      "team": "Edge",
      "status": "Active",
      "domain": "None",
      "product": "None",
      "has_config": true,
      "config_file": ".coderabbit.yaml",
      "has_coderabbit_reviews": true,
      "coderabbit_pr_count": 14,
      "coderabbit_first_review_count": 3,
      "coderabbit_first_review_pct": 21.4,
      "category": "fully_active",
      "last_updated": "2026-05-13T01:32:32.476038Z"
    },
    {
      "name": "ansible-operator-plugins",
      "url": "https://github.com/openshift/ansible-operator-plugins",
      "owner": "openshift",
      "repo": "ansible-operator-plugins",
      "team": "Application Platform",
      "status": "Active",
      "domain": "None",
      "product": "None",
      "has_config": false,
      "config_file": null,
      "has_coderabbit_reviews": true,
      "coderabbit_pr_count": 26,
      "coderabbit_first_review_count": 13,
      "coderabbit_first_review_pct": 50.0,
      "category": "reviewing_no_config",
      "last_updated": "2026-05-13T01:34:19.170069Z"
    },
    {
      "name": "cert-manager-operator",
      "url": "https://github.com/openshift/cert-manager-operator",
      "owner": "openshift",
      "repo": "cert-manager-operator",
      "team": "Application Platform",
      "status": "Active",
      "domain": "None",
      "product": "None",
      "has_config": false,
      "config_file": null,
      "has_coderabbit_reviews": true,
      "coderabbit_pr_count": 37,
      "coderabbit_first_review_count": 9,
      "coderabbit_first_review_pct": 24.3,
      "category": "reviewing_no_config",
      "last_updated": "2026-05-13T01:36:20.663542Z"
    },
    {
      "name": "external-secrets-operator",
      "url": "https://github.com/openshift/external-secrets-operator",
      "owner": "openshift",
      "repo": "external-secrets-operator",
      "team": "Application Platform",
      "status": "Active",
      "domain": "None",
      "product": "None",
      "has_config": false,
      "config_file": null,
      "has_coderabbit_reviews": true,
      "coderabbit_pr_count": 30,
      "coderabbit_first_review_count": 16,
      "coderabbit_first_review_pct": 53.3,
      "category": "reviewing_no_config",
      "last_updated": "2026-05-13T01:38:25.457554Z"
    },
    {
      "name": "lvm-operator",
      "url": "https://github.com/openshift/lvm-operator",
      "owner": "openshift",
      "repo": "lvm-operator",
      "team": "Edge",
      "status": "Active",
      "domain": "None",
      "product": "None",
      "has_config": true,
      "config_file": ".coderabbit.yaml",
      "has_coderabbit_reviews": true,
      "coderabbit_pr_count": 50,
      "coderabbit_first_review_count": 5,
      "coderabbit_first_review_pct": 10.0,
      "category": "fully_active",
      "last_updated": "2026-05-13T01:40:38.324126Z"
    },
    {
      "name": "microshift",
      "url": "https://github.com/openshift/microshift",
      "owner": "openshift",
      "repo": "microshift",
      "team": "Edge",
      "status": "Active",
      "domain": "None",
      "product": "None",
      "has_config": true,
      "config_file": ".coderabbit.yaml",
      "has_coderabbit_reviews": true,
      "coderabbit_pr_count": 25,
      "coderabbit_first_review_count": 10,
      "coderabbit_first_review_pct": 40.0,
      "category": "fully_active",
      "last_updated": "2026-05-13T01:42:38.378883Z"
    },
    {
      "name": "ocp-release-operator-sdk",
      "url": "https://github.com/openshift/ocp-release-operator-sdk",
      "owner": "openshift",
      "repo": "ocp-release-operator-sdk",
      "team": "Application Platform",
      "status": "Active",
      "domain": "None",
      "product": "None",
      "has_config": false,
      "config_file": null,
      "has_coderabbit_reviews": true,
      "coderabbit_pr_count": 16,
      "coderabbit_first_review_count": 3,
      "coderabbit_first_review_pct": 18.8,
      "category": "reviewing_no_config",
      "last_updated": "2026-05-13T01:44:09.810304Z"
    },
    {
      "name": "secrets-store-csi-driver",
      "url": "https://github.com/openshift/secrets-store-csi-driver",
      "owner": "openshift",
      "repo": "secrets-store-csi-driver",
      "team": "Application Platform",
      "status": "Active",
      "domain": "None",
      "product": "None",
      "has_config": false,
      "config_file": null,
      "has_coderabbit_reviews": true,
      "coderabbit_pr_count": 15,
      "coderabbit_first_review_count": 4,
      "coderabbit_first_review_pct": 26.7,
      "category": "reviewing_no_config",
      "last_updated": "2026-05-13T01:45:47.711747Z"
    },
    {
      "name": "secrets-store-csi-driver-operator",
      "url": "https://github.com/openshift/secrets-store-csi-driver-operator",
      "owner": "openshift",
      "repo": "secrets-store-csi-driver-operator",
      "team": "Application Platform",
      "status": "Active",
      "domain": "None",
      "product": "None",
      "has_config": false,
      "config_file": null,
      "has_coderabbit_reviews": true,
      "coderabbit_pr_count": 24,
      "coderabbit_first_review_count": 5,
      "coderabbit_first_review_pct": 20.8,
      "category": "reviewing_no_config",
      "last_updated": "2026-05-13T01:47:18.504227Z"
    },
    {
      "name": "spire-operator",
      "url": "https://github.com/openshift/spire-operator",
      "owner": "openshift",
      "repo": "spire-operator",
      "team": "Application Platform",
      "status": "Active",
      "domain": "None",
      "product": "None",
      "has_config": false,
      "config_file": null,
      "has_coderabbit_reviews": true,
      "coderabbit_pr_count": 45,
      "coderabbit_first_review_count": 18,
      "coderabbit_first_review_pct": 40.0,
      "category": "reviewing_no_config",
      "last_updated": "2026-05-13T01:50:04.593781Z"
    },
    {
      "name": "topolvm",
      "url": "https://github.com/openshift/topolvm",
      "owner": "openshift",
      "repo": "topolvm",
      "team": "Edge",
      "status": "Active",
      "domain": "None",
      "product": "None",
      "has_config": false,
      "config_file": null,
      "has_coderabbit_reviews": false,
      "coderabbit_pr_count": 0,
      "coderabbit_first_review_count": 0,
      "coderabbit_first_review_pct": 0,
      "category": "not_configured",
      "last_updated": "2026-05-13T01:51:50.424488Z"
    },
    {
      "name": "must-gather",
      "url": "https://github.com/openshift/must-gather",
      "owner": "openshift",
      "repo": "must-gather",
      "team": "Application Platform",
      "status": "Active",
      "domain": "None",
      "product": "None",
      "has_config": false,
      "config_file": null,
      "has_coderabbit_reviews": true,
      "coderabbit_pr_count": 19,
      "coderabbit_first_review_count": 8,
      "coderabbit_first_review_pct": 42.1,
      "category": "reviewing_no_config",
      "last_updated": "2026-05-13T01:53:45.443220Z"
    },
    {
      "name": "must-gather-operator",
      "url": "https://github.com/openshift/must-gather-operator",
      "owner": "openshift",
      "repo": "must-gather-operator",
      "team": "Application Platform",
      "status": "Active",
      "domain": "None",
      "product": "None",
      "has_config": false,
      "config_file": null,
      "has_coderabbit_reviews": true,
      "coderabbit_pr_count": 32,
      "coderabbit_first_review_count": 8,
      "coderabbit_first_review_pct": 25.0,
      "category": "reviewing_no_config",
      "last_updated": "2026-05-13T01:55:40.841758Z"
    },
    {
      "name": "hypershift",
      "url": "https://github.com/openshift/hypershift",
      "owner": "openshift",
      "repo": "hypershift",
      "team": "Multi Architecture",
      "status": "Active",
      "domain": "None",
      "product": "None",
      "has_config": true,
      "config_file": ".coderabbit.yaml",
      "has_coderabbit_reviews": true,
      "coderabbit_pr_count": 48,
      "coderabbit_first_review_count": 12,
      "coderabbit_first_review_pct": 25.0,
      "category": "fully_active",
      "last_updated": "2026-05-13T01:58:04.168189Z"
    },
    {
      "name": "machine-api-operator",
      "url": "https://github.com/openshift/machine-api-operator",
      "owner": "openshift",
      "repo": "machine-api-operator",
      "team": "Specialist Platform Team (SPLAT",
      "status": "Active",
      "domain": "None",
      "product": "None",
      "has_config": false,
      "config_file": null,
      "has_coderabbit_reviews": true,
      "coderabbit_pr_count": 34,
      "coderabbit_first_review_count": 9,
      "coderabbit_first_review_pct": 26.5,
      "category": "reviewing_no_config",
      "last_updated": "2026-05-13T02:00:00.120176Z"
    }
  ]
}